[
    {
        "title": "aa",
        "text": "aa"
    },
    {
        "title": "asd",
        "text": "asd"
    },
    {
        "title": "asdasd",
        "text": "asdas"
    },
    {
        "title": "New Test",
        "text": "Please Work"
    },
    {
        "title": "New Test",
        "text": "Please Work"
    },
    {
        "title": "New Test",
        "text": "Please Work"
    },
    {
        "title": "New Test",
        "text": "Please Work"
    },
    {
        "title": "New Test",
        "text": "Please Work"
    },
    {
        "title": "New Test",
        "text": "Please Work"
    },
    {
        "title": "New Test",
        "text": "Please Work"
    }
]